{
  "id": 3,
  "state": {
    "participants": 3,
    "threshold": 2
  },
  "public_aggregated_key": [
    0, 134, 252, 99, 188, 4, 93, 195, 201, 225, 183, 254, 152, 137, 3, 167, 159,
    118, 251, 125, 220, 104, 224, 101, 245, 190, 243, 91, 229, 218, 134, 135
  ],
  "own_public_share": [
    73, 224, 194, 176, 210, 196, 17, 205, 35, 189, 9, 165, 118, 142, 69, 231,
    26, 120, 160, 82, 244, 242, 13, 130, 186, 96, 56, 201, 181, 154, 118, 139
  ],
  "own_private_share": [
    126, 26, 65, 106, 148, 107, 24, 196, 163, 78, 160, 163, 173, 166, 117, 72,
    137, 167, 178, 29, 164, 71, 105, 29, 217, 233, 6, 75, 10, 179, 42, 11
  ],
  "participants_proofs": [
    {
      "Broadcast": {
        "participant_id": 1,
        "commitments": [
          [
            0, 108, 170, 123, 246, 216, 122, 246, 49, 122, 126, 99, 111, 61, 22,
            248, 250, 55, 151, 166, 51, 163, 42, 44, 124, 192, 138, 62, 9, 57,
            64, 185
          ],
          [
            99, 149, 143, 238, 215, 45, 127, 159, 187, 115, 61, 205, 236, 134,
            243, 191, 161, 138, 163, 120, 234, 120, 125, 55, 121, 2, 161, 102,
            169, 191, 129, 97
          ]
        ],
        "signature": [
          [
            142, 59, 119, 6, 101, 227, 85, 10, 147, 148, 164, 167, 142, 89, 132,
            16, 32, 40, 64, 64, 50, 12, 76, 38, 178, 14, 28, 126, 136, 40, 61,
            13
          ],
          [
            51, 9, 140, 110, 75, 131, 209, 230, 200, 15, 221, 63, 197, 25, 66,
            98, 182, 150, 224, 177, 80, 75, 238, 237, 29, 212, 112, 89, 27, 190,
            71, 1
          ]
        ]
      }
    },
    {
      "Broadcast": {
        "participant_id": 2,
        "commitments": [
          [
            2, 159, 149, 181, 173, 123, 155, 73, 116, 19, 232, 55, 125, 204, 90,
            187, 145, 152, 63, 199, 96, 141, 199, 139, 158, 27, 241, 245, 248,
            219, 103, 9
          ],
          [
            119, 118, 204, 234, 56, 42, 87, 219, 235, 89, 9, 247, 12, 250, 225,
            150, 212, 197, 220, 178, 124, 248, 238, 159, 108, 25, 68, 35, 239,
            113, 225, 193
          ]
        ],
        "signature": [
          [
            19, 8, 100, 117, 187, 58, 233, 194, 76, 120, 77, 196, 97, 79, 158,
            25, 172, 159, 35, 241, 53, 237, 139, 53, 229, 216, 128, 225, 138,
            164, 164, 13
          ],
          [
            99, 92, 152, 80, 64, 112, 128, 98, 174, 127, 113, 90, 167, 25, 57,
            232, 213, 159, 82, 244, 45, 148, 92, 245, 40, 185, 194, 160, 26,
            114, 47, 7
          ]
        ]
      }
    },
    {
      "Broadcast": {
        "participant_id": 3,
        "commitments": [
          [
            235, 223, 111, 159, 0, 238, 58, 73, 159, 148, 187, 73, 197, 66, 127,
            236, 149, 96, 166, 96, 94, 82, 121, 20, 245, 147, 233, 255, 113, 31,
            221, 97
          ],
          [
            23, 152, 116, 6, 245, 106, 64, 162, 105, 242, 34, 226, 115, 0, 144,
            103, 94, 222, 48, 94, 229, 52, 91, 153, 27, 48, 244, 177, 44, 180,
            99, 122
          ]
        ],
        "signature": [
          [
            207, 169, 67, 139, 84, 242, 122, 68, 200, 128, 56, 29, 180, 137, 17,
            217, 156, 180, 158, 124, 105, 11, 220, 36, 27, 105, 24, 83, 111, 92,
            94, 3
          ],
          [
            200, 157, 47, 229, 5, 176, 185, 85, 165, 7, 178, 231, 150, 143, 79,
            87, 200, 245, 75, 197, 54, 48, 182, 183, 61, 242, 199, 128, 38, 33,
            78, 15
          ]
        ]
      }
    }
  ],
  "subtype": "OPEN",
  "message": {
    "type": "state",
    "account": "nano_1168zjjur34xrh6y5fzym46i9bwzguxquq5aw3kzdhqmdhkxo3n96oxts7ox",
    "previous": "0",
    "representative": "nano_1168zjjur34xrh6y5fzym46i9bwzguxquq5aw3kzdhqmdhkxo3n96oxts7ox",
    "balance": "50000000000000000000000000",
    "link": "A5D0ACF7BE2A838E7EC87A7228C28B9F3A7C703E1AF2D8A6E74B4F9ECC20BFEA",
    "link_as_account": "nano_19kqrk7taqnprmy1hcchpkdcpfqnpm7knwdhn9qafhd7b94s99ofngf5ent1"
  }
}
